README.md
setup.py
directus_sdk/__init__.py
directus_sdk/api_client.py
directus_sdk/configuration.py
directus_sdk/rest.py
directus_sdk.egg-info/PKG-INFO
directus_sdk.egg-info/SOURCES.txt
directus_sdk.egg-info/dependency_links.txt
directus_sdk.egg-info/requires.txt
directus_sdk.egg-info/top_level.txt
directus_sdk/apis/__init__.py
directus_sdk/apis/activity_api.py
directus_sdk/apis/bookmarks_api.py
directus_sdk/apis/files_api.py
directus_sdk/apis/groups_api.py
directus_sdk/apis/messages_api.py
directus_sdk/apis/preferences_api.py
directus_sdk/apis/settings_api.py
directus_sdk/apis/tables_api.py
directus_sdk/apis/utils_api.py
directus_sdk/models/__init__.py
directus_sdk/models/get_activity.py
directus_sdk/models/get_activity_data.py
directus_sdk/models/get_activity_meta.py
directus_sdk/models/get_bookmark.py
directus_sdk/models/get_bookmarks.py
directus_sdk/models/get_bookmarks_data.py
directus_sdk/models/get_bookmarks_meta.py
directus_sdk/models/get_file.py
directus_sdk/models/get_files.py
directus_sdk/models/get_files_data.py
directus_sdk/models/get_group.py
directus_sdk/models/get_groups.py
directus_sdk/models/get_groups_data.py
directus_sdk/models/get_groups_data_data.py
directus_sdk/models/get_groups_data_meta.py
directus_sdk/models/get_message.py
directus_sdk/models/get_messages.py
directus_sdk/models/get_messages_data.py
directus_sdk/models/get_messages_meta.py
directus_sdk/models/get_messages_responses.py
directus_sdk/models/get_preferences.py
directus_sdk/models/get_preferences_data.py
directus_sdk/models/get_privileges.py
directus_sdk/models/get_privileges_data.py
directus_sdk/models/get_privileges_for_table.py
directus_sdk/models/get_settings.py
directus_sdk/models/get_settings_data.py
directus_sdk/models/get_settings_data_files.py
directus_sdk/models/get_settings_data_global.py
directus_sdk/models/get_settings_for.py
directus_sdk/models/get_settings_for_meta.py
directus_sdk/models/get_table.py
directus_sdk/models/get_table_column.py
directus_sdk/models/get_table_column_data.py
directus_sdk/models/get_table_columns.py
directus_sdk/models/get_table_columns_data.py
directus_sdk/models/get_table_data.py
