Metadata-Version: 1.0
Name: directus-sdk
Version: 1.1.1
Summary: directus.io
Home-page: https://directus.io
Author: UNKNOWN
Author-email: UNKNOWN
License: UNKNOWN
Keywords: Swagger,directus.io
Platform: UNKNOWN
